xSL01
